{
  "metadata": {
    "Created": "2017-04-04T13:05:32.1688388+01:00",
    "Modified": "2017-06-07T08:50:17.0814848+01:00",
    "User": "sbzjaa",
    "Complete": false,
    "Ignore": false
  },
  "data": [
    {
      "Name": "Ear",
      "Type": "PolyLine",
      "Points": [
        "1083,1032",
        "1058,1311"
      ]
    },
    {
      "Name": "Ear",
      "Type": "PolyLine",
      "Points": [
        "915,1064",
        "906.166975881262,1218.08719851577",
        "920,1391"
      ]
    },
    {
      "Name": "Ear",
      "Type": "PolyLine",
      "Points": [
        "848,1216",
        "838,1366",
        "842,1516"
      ]
    },
    {
      "Name": "Spikelet",
      "Type": "Point",
      "Points": [
        "839.800793650793,1504.5"
      ]
    },
    {
      "Name": "Spikelet",
      "Type": "Point",
      "Points": [
        "839.050793650793,1476.5"
      ]
    },
    {
      "Name": "Spikelet",
      "Type": "Point",
      "Points": [
        "837.550793650793,1450"
      ]
    },
    {
      "Name": "Spikelet",
      "Type": "Point",
      "Points": [
        "839.800793650793,1424.75"
      ]
    },
    {
      "Name": "Spikelet",
      "Type": "Point",
      "Points": [
        "841.050793650793,1392"
      ]
    },
    {
      "Name": "Spikelet",
      "Type": "Point",
      "Points": [
        "843.550793650793,1357.5"
      ]
    },
    {
      "Name": "Spikelet",
      "Type": "Point",
      "Points": [
        "845.800793650793,1323.25"
      ]
    },
    {
      "Name": "Spikelet",
      "Type": "Point",
      "Points": [
        "844.300793650793,1288"
      ]
    },
    {
      "Name": "Spikelet",
      "Type": "Point",
      "Points": [
        "847.550793650793,1257.75"
      ]
    },
    {
      "Name": "Spikelet",
      "Type": "Point",
      "Points": [
        "918.800793650793,1259"
      ]
    },
    {
      "Name": "Spikelet",
      "Type": "Point",
      "Points": [
        "902.300793650793,1272.75"
      ]
    },
    {
      "Name": "Spikelet",
      "Type": "Point",
      "Points": [
        "905.050793650793,1250"
      ]
    },
    {
      "Name": "Spikelet",
      "Type": "Point",
      "Points": [
        "917.300793650793,1233.25"
      ]
    },
    {
      "Name": "Spikelet",
      "Type": "Point",
      "Points": [
        "903.800793650793,1222"
      ]
    },
    {
      "Name": "Spikelet",
      "Type": "Point",
      "Points": [
        "912.800793650793,1206.5"
      ]
    },
    {
      "Name": "Spikelet",
      "Type": "Point",
      "Points": [
        "914.550793650793,1177.25"
      ]
    },
    {
      "Name": "Spikelet",
      "Type": "Point",
      "Points": [
        "903.550793650793,1160.25"
      ]
    },
    {
      "Name": "Spikelet",
      "Type": "Point",
      "Points": [
        "901.050793650793,1194"
      ]
    },
    {
      "Name": "Spikelet",
      "Type": "Point",
      "Points": [
        "913.550793650793,1144.5"
      ]
    },
    {
      "Name": "Spikelet",
      "Type": "Point",
      "Points": [
        "905.050793650793,1125.75"
      ]
    },
    {
      "Name": "Spikelet",
      "Type": "Point",
      "Points": [
        "914.550793650793,1111.5"
      ]
    },
    {
      "Name": "Spikelet",
      "Type": "Point",
      "Points": [
        "908.800793650793,1097.5"
      ]
    },
    {
      "Name": "Spikelet",
      "Type": "Point",
      "Points": [
        "914.300793650793,1082"
      ]
    },
    {
      "Name": "Spikelet",
      "Type": "Point",
      "Points": [
        "1064.90396825397,1291.40476190476"
      ]
    },
    {
      "Name": "Spikelet",
      "Type": "Point",
      "Points": [
        "1055.15396825397,1276.40476190476"
      ]
    },
    {
      "Name": "Spikelet",
      "Type": "Point",
      "Points": [
        "1067.40396825397,1268.90476190476"
      ]
    },
    {
      "Name": "Spikelet",
      "Type": "Point",
      "Points": [
        "1056.65396825397,1253.15476190476"
      ]
    },
    {
      "Name": "Spikelet",
      "Type": "Point",
      "Points": [
        "1066.65396825397,1242.90476190476"
      ]
    },
    {
      "Name": "Spikelet",
      "Type": "Point",
      "Points": [
        "1059.65396825397,1226.65476190476"
      ]
    },
    {
      "Name": "Spikelet",
      "Type": "Point",
      "Points": [
        "1063.40396825397,1139.65476190476"
      ]
    },
    {
      "Name": "Spikelet",
      "Type": "Point",
      "Points": [
        "1070.90396825397,1124.40476190476"
      ]
    },
    {
      "Name": "Spikelet",
      "Type": "Point",
      "Points": [
        "1067.90396825397,1109.40476190476"
      ]
    },
    {
      "Name": "Spikelet",
      "Type": "Point",
      "Points": [
        "1074.65396825397,1095.65476190476"
      ]
    },
    {
      "Name": "Spikelet",
      "Type": "Point",
      "Points": [
        "1073.65396825397,1077.90476190476"
      ]
    },
    {
      "Name": "Spikelet",
      "Type": "Point",
      "Points": [
        "1080.40396825397,1059.65476190476"
      ]
    },
    {
      "Name": "Spikelet",
      "Type": "Point",
      "Points": [
        "1071.42777777778,1481"
      ]
    },
    {
      "Name": "Spikelet",
      "Type": "Point",
      "Points": [
        "834.222222222223,1270.43333333333"
      ]
    },
    {
      "Name": "Spikelet",
      "Type": "Point",
      "Points": [
        "830.022222222223,1303.43333333333"
      ]
    },
    {
      "Name": "Spikelet",
      "Type": "Point",
      "Points": [
        "843.622222222223,1230.43333333333"
      ]
    },
    {
      "Name": "Spikelet",
      "Type": "Point",
      "Points": [
        "830.222222222223,1341.63333333333"
      ]
    },
    {
      "Name": "Spikelet",
      "Type": "Point",
      "Points": [
        "827.222222222223,1370.23333333333"
      ]
    },
    {
      "Name": "Spikelet",
      "Type": "Point",
      "Points": [
        "1074.39166666667,1509.6"
      ]
    },
    {
      "Name": "Spikelet",
      "Type": "Point",
      "Points": [
        "1078.59166666667,1463.2"
      ]
    },
    {
      "Name": "Awns",
      "Type": "Label",
      "Value": "False"
    }
  ]
}