{
  "metadata": {
    "Created": "2017-04-04T13:05:32.146823+01:00",
    "Modified": "2017-06-07T08:48:50.9624775+01:00",
    "User": "sbzjaa",
    "Complete": false,
    "Ignore": false
  },
  "data": [
    {
      "Name": "Ear",
      "Type": "PolyLine",
      "Points": [
        "1066,315",
        "1152,548"
      ]
    },
    {
      "Name": "Ear",
      "Type": "PolyLine",
      "Points": [
        "1443,302",
        "1359,520"
      ]
    },
    {
      "Name": "Ear",
      "Type": "PolyLine",
      "Points": [
        "1572,432",
        "1427,601"
      ]
    },
    {
      "Name": "Ear",
      "Type": "PolyLine",
      "Points": [
        "1539,350",
        "1502,480"
      ]
    },
    {
      "Name": "Ear",
      "Type": "PolyLine",
      "Points": [
        "1630,658",
        "1544,825"
      ]
    },
    {
      "Name": "Ear",
      "Type": "PolyLine",
      "Points": [
        "1468,728",
        "1445,855"
      ]
    },
    {
      "Name": "Ear",
      "Type": "PolyLine",
      "Points": [
        "1281,634",
        "1238,846"
      ]
    },
    {
      "Name": "Ear",
      "Type": "PolyLine",
      "Points": [
        "1249,641",
        "1230,835"
      ]
    },
    {
      "Name": "Ear",
      "Type": "PolyLine",
      "Points": [
        "1393.58134920635,532.246031746032",
        "1466.35912698413,633.357142857143",
        "1477.47023809524,742.246031746032"
      ]
    },
    {
      "Name": "Spikelet",
      "Type": "Point",
      "Points": [
        "1139.96349206349,519.925"
      ]
    },
    {
      "Name": "Spikelet",
      "Type": "Point",
      "Points": [
        "1125.96349206349,462.325"
      ]
    },
    {
      "Name": "Spikelet",
      "Type": "Point",
      "Points": [
        "1131.76349206349,489.725"
      ]
    },
    {
      "Name": "Spikelet",
      "Type": "Point",
      "Points": [
        "1114.36349206349,436.525"
      ]
    },
    {
      "Name": "Spikelet",
      "Type": "Point",
      "Points": [
        "1102.36349206349,405.125"
      ]
    },
    {
      "Name": "Spikelet",
      "Type": "Point",
      "Points": [
        "1093.16349206349,375.925"
      ]
    },
    {
      "Name": "Spikelet",
      "Type": "Point",
      "Points": [
        "1076.76349206349,348.525"
      ]
    },
    {
      "Name": "Spikelet",
      "Type": "Point",
      "Points": [
        "1271.26349206349,645.327777777778"
      ]
    },
    {
      "Name": "Spikelet",
      "Type": "Point",
      "Points": [
        "1277.59682539683,658.327777777778"
      ]
    },
    {
      "Name": "Spikelet",
      "Type": "Point",
      "Points": [
        "1265.59682539683,664.661111111111"
      ]
    },
    {
      "Name": "Spikelet",
      "Type": "Point",
      "Points": [
        "1274.93015873016,675.994444444444"
      ]
    },
    {
      "Name": "Spikelet",
      "Type": "Point",
      "Points": [
        "1260.59682539683,682.327777777778"
      ]
    },
    {
      "Name": "Spikelet",
      "Type": "Point",
      "Points": [
        "1268.59682539683,693.661111111111"
      ]
    },
    {
      "Name": "Spikelet",
      "Type": "Point",
      "Points": [
        "1258.93015873016,700.994444444444"
      ]
    },
    {
      "Name": "Spikelet",
      "Type": "Point",
      "Points": [
        "1232.15198412699,775.144444444445"
      ]
    },
    {
      "Name": "Spikelet",
      "Type": "Point",
      "Points": [
        "1226.95198412699,744.744444444445"
      ]
    },
    {
      "Name": "Spikelet",
      "Type": "Point",
      "Points": [
        "1236.79682539682,720.027777777778"
      ]
    },
    {
      "Name": "Spikelet",
      "Type": "Point",
      "Points": [
        "1244.19682539683,682.227777777778"
      ]
    },
    {
      "Name": "Spikelet",
      "Type": "Point",
      "Points": [
        "1228.19682539683,801.427777777778"
      ]
    },
    {
      "Name": "Spikelet",
      "Type": "Point",
      "Points": [
        "1363.90793650794,520.638888888889"
      ]
    },
    {
      "Name": "Spikelet",
      "Type": "Point",
      "Points": [
        "1384.70793650794,462.638888888889"
      ]
    },
    {
      "Name": "Spikelet",
      "Type": "Point",
      "Points": [
        "1366.70793650794,451.238888888889"
      ]
    },
    {
      "Name": "Spikelet",
      "Type": "Point",
      "Points": [
        "1378.50793650794,429.238888888889"
      ]
    },
    {
      "Name": "Spikelet",
      "Type": "Point",
      "Points": [
        "1388.70793650794,408.038888888889"
      ]
    },
    {
      "Name": "Spikelet",
      "Type": "Point",
      "Points": [
        "1412.90793650794,399.238888888889"
      ]
    },
    {
      "Name": "Spikelet",
      "Type": "Point",
      "Points": [
        "1395.90793650794,430.838888888889"
      ]
    },
    {
      "Name": "Spikelet",
      "Type": "Point",
      "Points": [
        "1400.30793650794,377.838888888889"
      ]
    },
    {
      "Name": "Spikelet",
      "Type": "Point",
      "Points": [
        "1421.10793650794,376.838888888889"
      ]
    },
    {
      "Name": "Spikelet",
      "Type": "Point",
      "Points": [
        "1428.70793650794,359.438888888889"
      ]
    },
    {
      "Name": "Spikelet",
      "Type": "Point",
      "Points": [
        "1421.70793650794,340.838888888889"
      ]
    },
    {
      "Name": "Spikelet",
      "Type": "Point",
      "Points": [
        "1436.10793650794,343.838888888889"
      ]
    },
    {
      "Name": "Spikelet",
      "Type": "Point",
      "Points": [
        "1428.30793650794,595.638888888889"
      ]
    },
    {
      "Name": "Spikelet",
      "Type": "Point",
      "Points": [
        "1445.30793650794,591.238888888889"
      ]
    },
    {
      "Name": "Spikelet",
      "Type": "Point",
      "Points": [
        "1439.30793650794,566.638888888889"
      ]
    },
    {
      "Name": "Spikelet",
      "Type": "Point",
      "Points": [
        "1461.90793650794,567.838888888889"
      ]
    },
    {
      "Name": "Spikelet",
      "Type": "Point",
      "Points": [
        "1454.70793650794,547.238888888889"
      ]
    },
    {
      "Name": "Spikelet",
      "Type": "Point",
      "Points": [
        "1473.70793650794,548.438888888889"
      ]
    },
    {
      "Name": "Spikelet",
      "Type": "Point",
      "Points": [
        "1470.90793650794,525.838888888889"
      ]
    },
    {
      "Name": "Spikelet",
      "Type": "Point",
      "Points": [
        "1489.70793650794,528.638888888889"
      ]
    },
    {
      "Name": "Spikelet",
      "Type": "Point",
      "Points": [
        "1504.10793650794,511.238888888889"
      ]
    },
    {
      "Name": "Spikelet",
      "Type": "Point",
      "Points": [
        "1488.10793650794,506.038888888889"
      ]
    },
    {
      "Name": "Spikelet",
      "Type": "Point",
      "Points": [
        "1508.50793650794,489.438888888889"
      ]
    },
    {
      "Name": "Spikelet",
      "Type": "Point",
      "Points": [
        "1525.50793650794,491.238888888889"
      ]
    },
    {
      "Name": "Spikelet",
      "Type": "Point",
      "Points": [
        "1526.30793650794,470.238888888889"
      ]
    },
    {
      "Name": "Spikelet",
      "Type": "Point",
      "Points": [
        "1541.90793650794,473.038888888889"
      ]
    },
    {
      "Name": "Spikelet",
      "Type": "Point",
      "Points": [
        "1541.70793650794,453.638888888889"
      ]
    },
    {
      "Name": "Spikelet",
      "Type": "Point",
      "Points": [
        "1562.30793650794,447.638888888889"
      ]
    },
    {
      "Name": "Spikelet",
      "Type": "Point",
      "Points": [
        "1562.30793650794,811.588888888889"
      ]
    },
    {
      "Name": "Spikelet",
      "Type": "Point",
      "Points": [
        "1554.55793650794,798.088888888889"
      ]
    },
    {
      "Name": "Spikelet",
      "Type": "Point",
      "Points": [
        "1568.80793650794,771.838888888889"
      ]
    },
    {
      "Name": "Spikelet",
      "Type": "Point",
      "Points": [
        "1580.80793650794,750.088888888889"
      ]
    },
    {
      "Name": "Spikelet",
      "Type": "Point",
      "Points": [
        "1593.80793650794,722.588888888889"
      ]
    },
    {
      "Name": "Spikelet",
      "Type": "Point",
      "Points": [
        "1610.05793650794,701.338888888889"
      ]
    },
    {
      "Name": "Spikelet",
      "Type": "Point",
      "Points": [
        "1621.05793650794,680.088888888889"
      ]
    },
    {
      "Name": "Spikelet",
      "Type": "Point",
      "Points": [
        "1573.61626984127,792.544444444444"
      ]
    },
    {
      "Name": "Spikelet",
      "Type": "Point",
      "Points": [
        "1587.81626984127,767.344444444444"
      ]
    },
    {
      "Name": "Spikelet",
      "Type": "Point",
      "Points": [
        "1601.21626984127,745.744444444444"
      ]
    },
    {
      "Name": "Spikelet",
      "Type": "Point",
      "Points": [
        "1449.0496031746,850.794444444444"
      ]
    },
    {
      "Name": "Spikelet",
      "Type": "Point",
      "Points": [
        "1455.6496031746,826.194444444444"
      ]
    },
    {
      "Name": "Spikelet",
      "Type": "Point",
      "Points": [
        "1462.6496031746,798.394444444444"
      ]
    },
    {
      "Name": "Spikelet",
      "Type": "Point",
      "Points": [
        "1465.2496031746,773.194444444444"
      ]
    },
    {
      "Name": "Spikelet",
      "Type": "Point",
      "Points": [
        "1467.0496031746,750.194444444444"
      ]
    },
    {
      "Name": "Spikelet",
      "Type": "Point",
      "Points": [
        "1071.25753968254,328.469841269841"
      ]
    },
    {
      "Name": "Spikelet",
      "Type": "Point",
      "Points": [
        "1280.74087301587,636.9"
      ]
    },
    {
      "Name": "Spikelet",
      "Type": "Point",
      "Points": [
        "1249.54087301587,659.9"
      ]
    },
    {
      "Name": "Spikelet",
      "Type": "Point",
      "Points": [
        "1425.41031746032,316.622222222222"
      ]
    },
    {
      "Name": "Spikelet",
      "Type": "Point",
      "Points": [
        "1442.41031746032,327.022222222222"
      ]
    },
    {
      "Name": "Spikelet",
      "Type": "Point",
      "Points": [
        "1440.61031746032,307.422222222222"
      ]
    },
    {
      "Name": "Spikelet",
      "Type": "Point",
      "Points": [
        "1515.89920634921,449.158333333333"
      ]
    },
    {
      "Name": "Spikelet",
      "Type": "Point",
      "Points": [
        "1521.29920634921,424.358333333333"
      ]
    },
    {
      "Name": "Spikelet",
      "Type": "Point",
      "Points": [
        "1524.69920634921,404.758333333333"
      ]
    },
    {
      "Name": "Spikelet",
      "Type": "Point",
      "Points": [
        "1529.69920634921,387.358333333333"
      ]
    },
    {
      "Name": "Spikelet",
      "Type": "Point",
      "Points": [
        "1533.49920634921,371.958333333333"
      ]
    },
    {
      "Name": "Spikelet",
      "Type": "Point",
      "Points": [
        "1539.09920634921,352.758333333333"
      ]
    },
    {
      "Name": "Spikelet",
      "Type": "Point",
      "Points": [
        "1504.89920634921,420.758333333333"
      ]
    },
    {
      "Name": "Spikelet",
      "Type": "Point",
      "Points": [
        "1500.69920634921,444.758333333333"
      ]
    },
    {
      "Name": "Spikelet",
      "Type": "Point",
      "Points": [
        "1495.69920634921,462.758333333333"
      ]
    },
    {
      "Name": "Spikelet",
      "Type": "Point",
      "Points": [
        "1475.21865079365,719.55"
      ]
    },
    {
      "Name": "Spikelet",
      "Type": "Point",
      "Points": [
        "1472.61865079365,693.55"
      ]
    },
    {
      "Name": "Spikelet",
      "Type": "Point",
      "Points": [
        "1458.41865079365,643.15"
      ]
    },
    {
      "Name": "Spikelet",
      "Type": "Point",
      "Points": [
        "1451.21865079365,618.35"
      ]
    },
    {
      "Name": "Spikelet",
      "Type": "Point",
      "Points": [
        "1477.41865079365,632.55"
      ]
    },
    {
      "Name": "Spikelet",
      "Type": "Point",
      "Points": [
        "1482.21865079365,658.95"
      ]
    },
    {
      "Name": "Spikelet",
      "Type": "Point",
      "Points": [
        "1488.41865079365,684.75"
      ]
    },
    {
      "Name": "Spikelet",
      "Type": "Point",
      "Points": [
        "1488.41865079365,711.55"
      ]
    },
    {
      "Name": "Spikelet",
      "Type": "Point",
      "Points": [
        "1486.01865079365,738.95"
      ]
    },
    {
      "Name": "Spikelet",
      "Type": "Point",
      "Points": [
        "1627.15198412699,665.705555555556"
      ]
    },
    {
      "Name": "Spikelet",
      "Type": "Point",
      "Points": [
        "1263.95198412699,717.344444444445"
      ]
    },
    {
      "Name": "Spikelet",
      "Type": "Point",
      "Points": [
        "1247.55198412699,725.144444444445"
      ]
    },
    {
      "Name": "Spikelet",
      "Type": "Point",
      "Points": [
        "1239.15198412699,750.744444444445"
      ]
    },
    {
      "Name": "Spikelet",
      "Type": "Point",
      "Points": [
        "1246.95198412699,770.544444444444"
      ]
    },
    {
      "Name": "Spikelet",
      "Type": "Point",
      "Points": [
        "1253.95198412699,743.544444444444"
      ]
    },
    {
      "Name": "Spikelet",
      "Type": "Point",
      "Points": [
        "1242.35198412699,793.144444444445"
      ]
    },
    {
      "Name": "Spikelet",
      "Type": "Point",
      "Points": [
        "1236.55198412699,827.144444444445"
      ]
    },
    {
      "Name": "Awns",
      "Type": "Label",
      "Value": "False"
    }
  ]
}